oslc4py_client/Link.py
oslc4py_client/OSLCPythonClient.py
oslc4py_client/OSLCResource.py
oslc4py_client/__init__.py
oslc4py_client/decorators.py
oslc4py_client/helpers.py
oslc4py_client/annotation_types/CreationFactory.py
oslc4py_client/annotation_types/Dialog.py
oslc4py_client/annotation_types/Occurs.py
oslc4py_client/annotation_types/RdfCollectionType.py
oslc4py_client/annotation_types/Representation.py
oslc4py_client/annotation_types/ValueType.py
oslc4py_client/annotation_types/__innit__.py
oslc4py_client-0.1.4.dist-info/LICENCE
oslc4py_client-0.1.4.dist-info/METADATA
oslc4py_client-0.1.4.dist-info/WHEEL
oslc4py_client-0.1.4.dist-info/top_level.txt
oslc4py_client-0.1.4.dist-info/RECORD
